poetry_stabs_package_sample/__init__.py
poetry_stabs_package_sample/importedsample/imported.py
poetry_stabs_package_sample/no_include__init__py.py
poetry_stabs_package_sample/py.typed
poetry_stabs_package_sample/sample.py
poetry_stabs_package_sample/sample2.py
poetry_stabs_package_sample/types/commonmodels/sampleModels.py
poetry_stabs_package_sample/types/sampleTypes.py
poetry_stabs_package_sample/utils/utilsample.py
poetry_stabs_package_sample-0.1.8.dist-info/METADATA
poetry_stabs_package_sample-0.1.8.dist-info/WHEEL
poetry_stabs_package_sample-0.1.8.dist-info/entry_points.txt
poetry_stabs_package_sample-0.1.8.dist-info/RECORD
