Metadata-Version: 2.1
Name: poetry-stabs-package-sample
Version: 0.1.8
Summary: sample package for poetry-stabs
Home-page: https://github.com/0num4
License: MIT
Author: 0num4
Author-email: r.oonuma@matsuri-tech.com
Requires-Python: >=3.12,<4.0
Classifier: Development Status :: 1 - Planning
Classifier: Intended Audience :: Developers
Classifier: Intended Audience :: Science/Research
Classifier: License :: Free for non-commercial use
Classifier: License :: OSI Approved :: MIT License
Classifier: Natural Language :: Japanese
Classifier: Operating System :: OS Independent
Classifier: Programming Language :: Python :: 3
Classifier: Programming Language :: Python :: 3.12
Classifier: Topic :: Scientific/Engineering
Classifier: Topic :: Software Development
Classifier: Typing :: Typed
Requires-Dist: poetry-dynamic-versioning (>=1.3.0,<2.0.0)
Project-URL: Repository, https://github.com/0num4/poetry-stabs-package-sample
